argpca/__init__.py
argpca/pca.py
argpca/utils.py
argpca-0.1.0.dist-info/licenses/LICENSE
argpca-0.1.0.dist-info/METADATA
argpca-0.1.0.dist-info/WHEEL
argpca-0.1.0.dist-info/top_level.txt
argpca-0.1.0.dist-info/RECORD
