Metadata-Version: 2.4
Name: argpca
Version: 0.1.0
Summary: Adaptive Reference-Guided PCA for high-dimension low-sample size data
Author-email: Dongsun Yoon <dsyoon@umich.edu>
License: MIT
Project-URL: Homepage, https://github.com/dsyoonstat/argpca
Requires-Python: >=3.9
License-File: LICENSE
Requires-Dist: numpy>=1.20
Provides-Extra: examples
Requires-Dist: pandas; extra == "examples"
Requires-Dist: matplotlib; extra == "examples"
Provides-Extra: dev
Requires-Dist: pytest; extra == "dev"
Dynamic: license-file
